quantus/__init__.py
quantus/evaluation.py
quantus/py.typed
quantus/functions/__init__.py
quantus/functions/complexity_func.py
quantus/functions/discretise_func.py
quantus/functions/explanation_func.py
quantus/functions/loss_func.py
quantus/functions/mosaic_func.py
quantus/functions/n_bins_func.py
quantus/functions/norm_func.py
quantus/functions/normalise_func.py
quantus/functions/perturb_func.py
quantus/functions/similarity_func.py
quantus/helpers/__init__.py
quantus/helpers/asserts.py
quantus/helpers/constants.py
quantus/helpers/enums.py
quantus/helpers/perturbation_utils.py
quantus/helpers/plotting.py
quantus/helpers/utils.py
quantus/helpers/warn.py
quantus/helpers/model/__init__.py
quantus/helpers/model/model_interface.py
quantus/helpers/model/models.py
quantus/helpers/model/pytorch_model.py
quantus/helpers/model/tf_model.py
quantus/metrics/__init__.py
quantus/metrics/base.py
quantus/metrics/base_batched.py
quantus/metrics/axiomatic/__init__.py
quantus/metrics/axiomatic/completeness.py
quantus/metrics/axiomatic/input_invariance.py
quantus/metrics/axiomatic/non_sensitivity.py
quantus/metrics/complexity/__init__.py
quantus/metrics/complexity/complexity.py
quantus/metrics/complexity/effective_complexity.py
quantus/metrics/complexity/sparseness.py
quantus/metrics/faithfulness/__init__.py
quantus/metrics/faithfulness/faithfulness_correlation.py
quantus/metrics/faithfulness/faithfulness_estimate.py
quantus/metrics/faithfulness/infidelity.py
quantus/metrics/faithfulness/irof.py
quantus/metrics/faithfulness/monotonicity.py
quantus/metrics/faithfulness/monotonicity_correlation.py
quantus/metrics/faithfulness/pixel_flipping.py
quantus/metrics/faithfulness/region_perturbation.py
quantus/metrics/faithfulness/road.py
quantus/metrics/faithfulness/selectivity.py
quantus/metrics/faithfulness/sensitivity_n.py
quantus/metrics/faithfulness/sufficiency.py
quantus/metrics/localisation/__init__.py
quantus/metrics/localisation/attribution_localisation.py
quantus-0.5.3.dist-info/LICENSE
quantus-0.5.3.dist-info/WHEEL
quantus-0.5.3.dist-info/METADATA
quantus-0.5.3.dist-info/RECORD
