Metadata-Version: 2.1
Name: quantus
Version: 0.5.3
Summary: A metrics toolkit to evaluate neural network explanations.
Keywords: explainable ai,xai,machine learning,deep learning
Author-email: Anna Hedstrom <hedstroem.anna@gmail.com>
Maintainer-email: Anna Hedstrom <hedstroem.anna@gmail.com>
Requires-Python: >=3.7
Classifier: Development Status :: 4 - Beta
Classifier: Intended Audience :: Education
Classifier: Intended Audience :: Science/Research
Classifier: Intended Audience :: Developers
Classifier: License :: OSI Approved :: GNU General Public License v3 (GPLv3)
Classifier: Programming Language :: Python :: 3 :: Only
Classifier: Topic :: Software Development :: Libraries :: Python Modules
Classifier: Topic :: Scientific/Engineering :: Artificial Intelligence
Requires-Dist: numpy>=1.19.5
Requires-Dist: pandas<=1.3.3; python_version == '3.7'
Requires-Dist: pandas>=1.5.3; python_version > '3.7'
Requires-Dist: opencv-python>=4.5.5.62
Requires-Dist: scikit-image>=0.19.3
Requires-Dist: scikit-learn>=0.24.2
Requires-Dist: scipy>=1.7.3
Requires-Dist: tqdm>=4.62.3
Requires-Dist: matplotlib>=3.3.4
Requires-Dist: typing_extensions; python_version <= '3.8'
Requires-Dist: quantus[torch] ; extra == "captum"
Requires-Dist: captum>=0.6.0 ; extra == "captum"
Requires-Dist: quantus[captum,tf_explain,zennit] ; extra == "full"
Requires-Dist: tensorflow>=2.5.0 ; extra == "tensorflow" and ( python_version == '3.7')
Requires-Dist: tensorflow>=2.12.0 ; extra == "tensorflow" and ( sys_platform != 'darwin' and python_version > '3.7')
Requires-Dist: tensorflow_macos>=2.9.0 ; extra == "tensorflow" and ( sys_platform == 'darwin' and python_version > '3.7')
Requires-Dist: captum>=0.6.0 ; extra == "tests"
Requires-Dist: coverage>=7.2.3 ; extra == "tests"
Requires-Dist: flake8<=4.0.1 ; extra == "tests" and ( python_version == '3.7')
Requires-Dist: flake8>=6.0.0 ; extra == "tests" and ( python_version > '3.7')
Requires-Dist: pytest>=7.3.1 ; extra == "tests"
Requires-Dist: pytest-cov>=4.0.0 ; extra == "tests"
Requires-Dist: pytest-lazy-fixture>=0.6.3 ; extra == "tests"
Requires-Dist: pytest-mock==3.10.0 ; extra == "tests"
Requires-Dist: pytest_xdist ; extra == "tests"
Requires-Dist: tf-explain>=0.3.1 ; extra == "tests"
Requires-Dist: zennit>=0.4.5 ; extra == "tests" and ( python_version >= '3.7')
Requires-Dist: tensorflow>=2.5.0 ; extra == "tests" and ( python_version == '3.7')
Requires-Dist: tensorflow>=2.12.0 ; extra == "tests" and ( sys_platform != 'darwin' and python_version > '3.7')
Requires-Dist: tensorflow_macos>=2.9.0 ; extra == "tests" and ( sys_platform == 'darwin' and python_version > '3.7')
Requires-Dist: torch<=1.9.0 ; extra == "tests" and ( python_version == '3.7')
Requires-Dist: torch>=1.13.1 ; extra == "tests" and ( sys_platform != 'linux' and python_version > '3.7')
Requires-Dist: torch>=1.13.1, <2.0.0 ; extra == "tests" and ( sys_platform == 'linux' and python_version > '3.7' and python_version <= '3.10')
Requires-Dist: torch>=2.0.0 ; extra == "tests" and ( sys_platform == 'linux' and python_version >= '3.11')
Requires-Dist: torchvision<=0.12.0 ; extra == "tests" and ( python_version == '3.7')
Requires-Dist: torchvision>=0.15.1 ; extra == "tests" and ( sys_platform != 'linux' and python_version > '3.7')
Requires-Dist: torchvision>=0.14.0, <0.15.1 ; extra == "tests" and ( sys_platform == 'linux' and python_version > '3.7' and python_version <= '3.10')
Requires-Dist: torchvision>=0.15.1 ; extra == "tests" and ( sys_platform == 'linux' and python_version >= '3.11')
Requires-Dist: quantus[tensorflow] ; extra == "tf_explain"
Requires-Dist: tf-explain>=0.3.1 ; extra == "tf_explain"
Requires-Dist: torch<=1.11.0 ; extra == "torch" and ( python_version == '3.7')
Requires-Dist: torch>=1.13.1 ; extra == "torch" and ( sys_platform != 'linux' and python_version > '3.7')
Requires-Dist: torch>=1.13.1, <2.0.0 ; extra == "torch" and ( sys_platform == 'linux' and python_version > '3.7' and python_version <= '3.10')
Requires-Dist: torch>=2.0.0 ; extra == "torch" and ( sys_platform == 'linux' and python_version >= '3.11')
Requires-Dist: torchvision<=0.12.0 ; extra == "torch" and ( python_version == '3.7')
Requires-Dist: torchvision>=0.15.1 ; extra == "torch" and ( sys_platform != 'linux' and python_version > '3.7')
Requires-Dist: torchvision>=0.14.0, <0.15.1 ; extra == "torch" and ( sys_platform == 'linux' and python_version > '3.7' and python_version <= '3.10')
Requires-Dist: torchvision>=0.15.1 ; extra == "torch" and ( sys_platform == 'linux' and python_version >= '3.11')
Requires-Dist: quantus[torch] ; extra == "zennit"
Requires-Dist: zennit>=0.5.1 ; extra == "zennit"
Project-URL: Documentation, https://quantus.readthedocs.io/en/latest/
Project-URL: Source, https://github.com/understandable-machine-intelligence-lab/Quantus
Provides-Extra: captum
Provides-Extra: full
Provides-Extra: tensorflow
Provides-Extra: tests
Provides-Extra: tf_explain
Provides-Extra: torch
Provides-Extra: zennit
